world_machine/__init__.py
world_machine/current_version.py
world_machine/wm_builder.py
world_machine/world_machine.py
world_machine/data/__init__.py
world_machine/data/dataloader.py
world_machine/data/dataset.py
world_machine/evaluate/__init__.py
world_machine/evaluate/metrics_generator.py
world_machine/layers/__init__.py
world_machine/layers/adaln_zero_block.py
world_machine/layers/attention.py
world_machine/layers/block_container.py
world_machine/layers/clamp.py
world_machine/layers/conditioning_block.py
world_machine/layers/ltanh.py
world_machine/layers/modulate.py
world_machine/layers/pointwise_feedforward.py
world_machine/layers/sin_tanh.py
world_machine/layers/sine.py
world_machine/layers/transform_decoder_block.py
world_machine/layers/positional_encoder/__init__.py
world_machine/layers/positional_encoder/alibi.py
world_machine/layers/positional_encoder/create.py
world_machine/layers/positional_encoder/positional_encoder.py
world_machine/layers/positional_encoder/sine.py
world_machine/profile/__init__.py
world_machine/profile/profile_range.py
world_machine/profile/nvtx/__init__.py
world_machine/profile/nvtx/annotate_se.py
world_machine/profile/nvtx/colors.py
world_machine/profile/nvtx/mock.py
world_machine/train/__init__.py
world_machine/train/criterion_set.py
world_machine/train/mode.py
world_machine/train/scheduler.py
world_machine/train/trainer.py
world_machine/train/stages/__init__.py
world_machine/train/stages/early_stopper.py
world_machine/train/stages/gradient_accumulator.py
world_machine/train/stages/lambda_stage.py
world_machine/train/stages/local_setter.py
world_machine/train/stages/loss_manager.py
world_machine/train/stages/lrscheduler_step.py
world_machine/train/stages/noise_adder.py
world_machine/train/stages/prepare_model.py
world_machine/train/stages/sensory_masker.py
world_machine/train/stages/sequence_breaker.py
world_machine/train/stages/short_time_recaller.py
world_machine/train/stages/simple_optimizer.py
world_machine-0.2.dist-info/licenses/LICENSE
world_machine-0.2.dist-info/METADATA
world_machine-0.2.dist-info/WHEEL
world_machine-0.2.dist-info/top_level.txt
world_machine-0.2.dist-info/RECORD
