Metadata-Version: 2.4
Name: world_machine
Version: 0.2
Summary: Investigating the concept and creation of computational world models.
Author-email: Elton Cardoso do Nascimento <e233840@dac.unicamp.br>
Project-URL: Homepage, https://h-iaac.github.io/WorldMachine/
Project-URL: Bug Tracker, https://github.com/H-IAAC/WorldMachine/issues
Classifier: Programming Language :: Python :: 3
Classifier: Operating System :: OS Independent
Classifier: Topic :: Scientific/Engineering
Classifier: Topic :: Scientific/Engineering :: Artificial Intelligence
Classifier: Intended Audience :: Science/Research
Requires-Python: >=3.10
License-File: LICENSE
Requires-Dist: torch
Requires-Dist: tensordict
Requires-Dist: numba
Dynamic: license-file
